vectorview/__init__.py
vectorview-1.1.0.dist-info/METADATA
vectorview-1.1.0.dist-info/WHEEL
vectorview-1.1.0.dist-info/top_level.txt
vectorview-1.1.0.dist-info/RECORD
